{
  "parent": "aprandomizer:archipelago/bake_bread",
  "display": {
    "icon": {
      "item": "minecraft:cake"
    },
    "title": {
      "text": "The Lie"
    },
    "description": {
      "text": "Bake cake using wheat, sugar, milk, and eggs!"
    },
    "frame": "challenge",
    "show_toast": true,
    "announce_to_chat": false,
    "hidden": false
  },
  "criteria": {
    "eat_cake": {
      "trigger": "minecraft:item_used_on_block",
      "conditions": {
        "location": {
          "block": {
            "blocks": ["minecraft:cake"]
          }
        }
      }
    }
  },
  "requirements": [
    [
      "eat_cake"
    ]
  ]
}