{
  "name": "aprandomizer:village/nether/houses",
  "fallback": "aprandomizer:village/nether/terminators",
  "elements": [
    {
      "weight": 2,
      "element": {
        "location": "aprandomizer:village/nether/houses/nether_small_house_1",
        "processors": "minecraft:empty",
        "projection": "rigid",
        "element_type": "minecraft:single_pool_element"
      }
    },
    {
      "weight": 2,
      "element": {
        "location": "aprandomizer:village/nether/houses/nether_small_house_2",
        "processors": "minecraft:empty",
        "projection": "rigid",
        "element_type": "minecraft:single_pool_element"
      }
    },
    {
      "weight": 2,
      "element": {
        "location": "aprandomizer:village/nether/houses/nether_small_house_3",
        "processors": "minecraft:empty",
        "projection": "rigid",
        "element_type": "minecraft:single_pool_element"
      }
    },
    {
      "weight": 2,
      "element": {
        "location": "aprandomizer:village/nether/houses/nether_small_house_4",
        "processors": "minecraft:empty",
        "projection": "rigid",
        "element_type": "minecraft:single_pool_element"
      }
    },
    {
      "weight": 2,
      "element": {
        "location": "aprandomizer:village/nether/houses/nether_small_house_5",
        "processors": "minecraft:empty",
        "projection": "rigid",
        "element_type": "minecraft:single_pool_element"
      }
    },
    {
      "weight": 1,
      "element": {
        "location": "aprandomizer:village/nether/houses/nether_small_house_6",
        "processors": "minecraft:empty",
        "projection": "rigid",
        "element_type": "minecraft:single_pool_element"
      }
    },
    {
      "weight": 2,
      "element": {
        "location": "aprandomizer:village/nether/houses/nether_small_house_7",
        "processors": "minecraft:empty",
        "projection": "rigid",
        "element_type": "minecraft:single_pool_element"
      }
    },
    {
      "weight": 3,
      "element": {
        "location": "aprandomizer:village/nether/houses/nether_small_house_8",
        "processors": "minecraft:empty",
        "projection": "rigid",
        "element_type": "minecraft:single_pool_element"
      }
    },
    {
      "weight": 2,
      "element": {
        "location": "aprandomizer:village/nether/houses/nether_medium_house_1",
        "processors": "minecraft:empty",
        "projection": "rigid",
        "element_type": "minecraft:single_pool_element"
      }
    },
    {
      "weight": 2,
      "element": {
        "location": "aprandomizer:village/nether/houses/nether_medium_house_2",
        "processors": "minecraft:empty",
        "projection": "rigid",
        "element_type": "minecraft:single_pool_element"
      }
    },
    {
      "weight": 2,
      "element": {
        "location": "aprandomizer:village/nether/houses/nether_big_house_1",
        "processors": "minecraft:empty",
        "projection": "rigid",
        "element_type": "minecraft:single_pool_element"
      }
    },
    {
      "weight": 2,
      "element": {
        "location": "aprandomizer:village/nether/houses/nether_butcher_shop_1",
        "processors": "minecraft:empty",
        "projection": "rigid",
        "element_type": "minecraft:single_pool_element"
      }
    },
    {
      "weight": 2,
      "element": {
        "location": "aprandomizer:village/nether/houses/nether_butcher_shop_2",
        "processors": "minecraft:empty",
        "projection": "rigid",
        "element_type": "minecraft:single_pool_element"
      }
    },
    {
      "weight": 2,
      "element": {
        "location": "aprandomizer:village/nether/houses/nether_tool_smith_1",
        "processors": "minecraft:empty",
        "projection": "rigid",
        "element_type": "minecraft:single_pool_element"
      }
    },
    {
      "weight": 2,
      "element": {
        "location": "aprandomizer:village/nether/houses/nether_fletcher_house_1",
        "processors": "minecraft:empty",
        "projection": "rigid",
        "element_type": "minecraft:single_pool_element"
      }
    },
    {
      "weight": 2,
      "element": {
        "location": "aprandomizer:village/nether/houses/nether_shepherds_house_1",
        "processors": "minecraft:empty",
        "projection": "rigid",
        "element_type": "minecraft:single_pool_element"
      }
    },
    {
      "weight": 2,
      "element": {
        "location": "aprandomizer:village/nether/houses/nether_armorer_house_1",
        "processors": "minecraft:empty",
        "projection": "rigid",
        "element_type": "minecraft:single_pool_element"
      }
    },
    {
      "weight": 2,
      "element": {
        "location": "aprandomizer:village/nether/houses/nether_fisher_cottage_1",
        "processors": "minecraft:empty",
        "projection": "rigid",
        "element_type": "minecraft:single_pool_element"
      }
    },
    {
      "weight": 2,
      "element": {
        "location": "aprandomizer:village/nether/houses/nether_tannery_1",
        "processors": "minecraft:empty",
        "projection": "rigid",
        "element_type": "minecraft:single_pool_element"
      }
    },
    {
      "weight": 1,
      "element": {
        "location": "aprandomizer:village/nether/houses/nether_cartographer_1",
        "processors": "minecraft:empty",
        "projection": "rigid",
        "element_type": "minecraft:single_pool_element"
      }
    },
    {
      "weight": 5,
      "element": {
        "location": "aprandomizer:village/nether/houses/nether_library_1",
        "processors": "minecraft:empty",
        "projection": "rigid",
        "element_type": "minecraft:single_pool_element"
      }
    },
    {
      "weight": 1,
      "element": {
        "location": "aprandomizer:village/nether/houses/nether_library_2",
        "processors": "minecraft:empty",
        "projection": "rigid",
        "element_type": "minecraft:single_pool_element"
      }
    },
    {
      "weight": 2,
      "element": {
        "location": "aprandomizer:village/nether/houses/nether_masons_house_1",
        "processors": "minecraft:empty",
        "projection": "rigid",
        "element_type": "minecraft:single_pool_element"
      }
    },
    {
      "weight": 2,
      "element": {
        "location": "aprandomizer:village/nether/houses/nether_weaponsmith_1",
        "processors": "minecraft:empty",
        "projection": "rigid",
        "element_type": "minecraft:single_pool_element"
      }
    },
    {
      "weight": 2,
      "element": {
        "location": "aprandomizer:village/nether/houses/nether_temple_3",
        "processors": "minecraft:empty",
        "projection": "rigid",
        "element_type": "minecraft:single_pool_element"
      }
    },
    {
      "weight": 2,
      "element": {
        "location": "aprandomizer:village/nether/houses/nether_temple_4",
        "processors": "minecraft:empty",
        "projection": "rigid",
        "element_type": "minecraft:single_pool_element"
      }
    },
    {
      "weight": 2,
      "element": {
        "location": "aprandomizer:village/nether/houses/nether_stable_1",
        "processors": "minecraft:empty",
        "projection": "rigid",
        "element_type": "minecraft:single_pool_element"
      }
    },
    {
      "weight": 2,
      "element": {
        "location": "aprandomizer:village/nether/houses/nether_stable_2",
        "processors": "minecraft:empty",
        "projection": "rigid",
        "element_type": "minecraft:single_pool_element"
      }
    },
    {
      "weight": 4,
      "element": {
        "location": "aprandomizer:village/nether/houses/nether_large_farm_1",
        "processors": "minecraft:empty",
        "projection": "rigid",
        "element_type": "minecraft:single_pool_element"
      }
    },
    {
      "weight": 4,
      "element": {
        "location": "aprandomizer:village/nether/houses/nether_small_farm_1",
        "processors": "minecraft:empty",
        "projection": "rigid",
        "element_type": "minecraft:single_pool_element"
      }
    },
    {
      "weight": 1,
      "element": {
        "location": "aprandomizer:village/nether/houses/nether_animal_pen_1",
        "processors": "minecraft:empty",
        "projection": "rigid",
        "element_type": "minecraft:single_pool_element"
      }
    },
    {
      "weight": 1,
      "element": {
        "location": "aprandomizer:village/nether/houses/nether_animal_pen_2",
        "processors": "minecraft:empty",
        "projection": "rigid",
        "element_type": "minecraft:single_pool_element"
      }
    },
    {
      "weight": 5,
      "element": {
        "location": "aprandomizer:village/nether/houses/nether_animal_pen_3",
        "processors": "minecraft:empty",
        "projection": "rigid",
        "element_type": "minecraft:single_pool_element"
      }
    },
    {
      "weight": 1,
      "element": {
        "location": "aprandomizer:village/nether/houses/nether_accessory_1",
        "processors": "minecraft:empty",
        "projection": "rigid",
        "element_type": "minecraft:single_pool_element"
      }
    },
    {
      "weight": 3,
      "element": {
        "location": "aprandomizer:village/nether/houses/nether_meeting_point_4",
        "processors": "minecraft:empty",
        "projection": "rigid",
        "element_type": "minecraft:single_pool_element"
      }
    },
    {
      "weight": 1,
      "element": {
        "location": "aprandomizer:village/nether/houses/nether_meeting_point_5",
        "processors": "minecraft:empty",
        "projection": "rigid",
        "element_type": "minecraft:single_pool_element"
      }
    },
    {
      "weight": 10,
      "element": {
        "element_type": "minecraft:empty_pool_element"
      }
    }
  ]
}